DataversePython/DataverseClient.py
DataversePython/__init__.py
DataversePython/api_client.py
DataversePython/auth/__init__.py
DataversePython/auth/base.py
DataversePython/auth/msal_client_secret.py
DataversePython/auth/msal_interactive.py
dataversepython-1.1.0.dist-info/licenses/LICENSE
dataversepython-1.1.0.dist-info/METADATA
dataversepython-1.1.0.dist-info/WHEEL
dataversepython-1.1.0.dist-info/top_level.txt
dataversepython-1.1.0.dist-info/RECORD
