Metadata-Version: 2.4
Name: DataversePython
Version: 1.1.0
Summary: A Dataverse client for Python
Home-page: https://github.com/fabipfr/DataversePython
Author: fabipfr
Author-email: contact@fabianpfriem.com
Requires-Python: >=3.10
License-File: LICENSE
Requires-Dist: requests>=2.32.4
Requires-Dist: pandas>=2.3.1
Requires-Dist: numpy>=2.3.2
Requires-Dist: msal>=1.33.0
Dynamic: author
Dynamic: author-email
Dynamic: description
Dynamic: description-content-type
Dynamic: home-page
Dynamic: license-file
Dynamic: requires-dist
Dynamic: requires-python
Dynamic: summary
